{"cameraMode":{"drawMode":0,"name":"Shaded","section":"Shading Mode"},"sceneLighting":true,"audioPlay":false,"sceneViewState":{"showFog":true,"showMaterialUpdate":false,"showSkybox":true,"showFlares":true,"showImageEffects":true,"showParticleSystems":true},"in2DMode":false,"pivot":{"x":0.6194173097610474,"y":1.040130615234375,"z":-0.8306221961975098},"rotation":{"x":-0.30348488688468935,"y":-0.14870014786720277,"z":0.04801274463534355,"w":-0.9399362206459045},"size":2.0290377140045168,"orthographic":false}